Metadata-Version: 2.1
Name: ayoubcalc
Version: 1.1
Summary: simpl library by python 
Home-page: UNKNOWN
Author: ayoub slassi
License: UNKNOWN
Platform: UNKNOWN
Classifier: Programming Language :: Python :: 3
Classifier: Operating System :: OS Independent
Classifier: License :: OSI Approved :: MIT License
License-File: LICENSE.txt
